{"name":"Iptables","_id":"cm0xoldbz007g22sn3m6a1a4s","slug":"Iptables","path":"tags/Iptables/","permalink":"https://yuekang.org.cn/tags/Iptables/","posts":[{"title":"Centos 端口转发管理","date":"2018-12-14T02:12:47.000Z","slug":"2018-12-14-Centos-端口转发管理","published":true,"updated":"2024-09-11T07:55:00.243Z","_id":"cm0xoldbe002k22snhil05ick","layout":"post","photos":[],"excerpt":"","path":"2018/12/14/2018-12-14-Centos-端口转发管理/","permalink":"https://yuekang.org.cn/2018/12/14/2018-12-14-Centos-%E7%AB%AF%E5%8F%A3%E8%BD%AC%E5%8F%91%E7%AE%A1%E7%90%86/","__post":true}],"length":1}