{"title":"反馈专区","date":"2017-02-10T04:17:05.000Z","source":"feedback/index.md","raw":"---\ntitle: 反馈专区\ndate: 2017-02-10 12:17:05\ntag: 反馈\n---\n\n欢迎大家在这里给我反馈，我非常的感谢你们的支持！\n","updated":"2024-09-02T09:06:11.434Z","_id":"cm0oxo4sm00025asn1m4s6v6e","comments":true,"layout":"page","html":"<p>欢迎大家在这里给我反馈，我非常的感谢你们的支持！</p>\n","excerpt":"","more":"<p>欢迎大家在这里给我反馈，我非常的感谢你们的支持！</p>\n","path":"feedback/index.html","permalink":"https://yuekang.org.cn/feedback/index.html","prev":null,"next":null,"__page":true}